<?xml version="1.0" encoding="UTF-8"?><record_update table="sys_script_include">
    <sys_script_include action="DELETE">
        <access>package_private</access>
        <active>true</active>
        <api_name>x_snc_ride.GetBaseRecordTables</api_name>
        <caller_access/>
        <client_callable>false</client_callable>
        <description>Returns an array of table names that contain "base" tables. "Base" tables are tables which serve only as base tables for more specific record tables.&#13;
E.g., the "sys_hub_flow_block" is a base table from which e.g. "sys_hub_flow" is derived.</description>
        <name>GetBaseRecordTables</name>
        <script><![CDATA[function GetBaseRecordTables()
{
	var aBaseRecordTables = [
		'sys_hub_flow_block',
		'sys_hub_flow_base',
		'sys_hub_action_type_base'
		];
	return aBaseRecordTables;
}]]></script>
        <sys_class_name>sys_script_include</sys_class_name>
        <sys_created_by>admin</sys_created_by>
        <sys_created_on>2024-11-25 16:56:51</sys_created_on>
        <sys_id>cc68119683465a1000d5ccc0deaad3c3</sys_id>
        <sys_mod_count>4</sys_mod_count>
        <sys_name>GetBaseRecordTables</sys_name>
        <sys_package display_value="R-IDE WORK IN PROGRESS" source="x_snc_ide">b598b2161b2e2510cd6153d16b4bcb08</sys_package>
        <sys_policy>read</sys_policy>
        <sys_scope display_value="R-IDE WORK IN PROGRESS">b598b2161b2e2510cd6153d16b4bcb08</sys_scope>
        <sys_update_name>sys_script_include_cc68119683465a1000d5ccc0deaad3c3</sys_update_name>
        <sys_updated_by>admin</sys_updated_by>
        <sys_updated_on>2024-12-08 00:03:52</sys_updated_on>
    </sys_script_include>
    <sys_update_version action="INSERT_OR_UPDATE">
        <action>DELETE</action>
        <application display_value="R-IDE WORK IN PROGRESS">b598b2161b2e2510cd6153d16b4bcb08</application>
        <file_path/>
        <instance_id>00dfd44b1b640a14a43dcb7b234bcbf2</instance_id>
        <instance_name>wildwashington</instance_name>
        <name>sys_script_include_cc68119683465a1000d5ccc0deaad3c3</name>
        <payload>&lt;?xml version="1.0" encoding="UTF-8"?&gt;&lt;record_update table="sys_script_include"&gt;&lt;sys_script_include action="INSERT_OR_UPDATE"&gt;&lt;access&gt;package_private&lt;/access&gt;&lt;active&gt;true&lt;/active&gt;&lt;api_name&gt;x_snc_ride.GetBaseRecordTables&lt;/api_name&gt;&lt;caller_access/&gt;&lt;client_callable&gt;false&lt;/client_callable&gt;&lt;description&gt;Returns an array of table names that contain "base" tables. "Base" tables are tables which serve only as base tables for more specific record tables.&amp;#13;
E.g., the "sys_hub_flow_block" is a base table from which e.g. "sys_hub_flow" is derived.&lt;/description&gt;&lt;name&gt;GetBaseRecordTables&lt;/name&gt;&lt;script&gt;&lt;![CDATA[function GetBaseRecordTables()
{
	var aBaseRecordTables = [
		'sys_hub_flow_block',
		'sys_hub_flow_base',
		'sys_hub_action_type_base'
		];
	return aBaseRecordTables;
}]]&gt;&lt;/script&gt;&lt;sys_class_name&gt;sys_script_include&lt;/sys_class_name&gt;&lt;sys_created_by&gt;admin&lt;/sys_created_by&gt;&lt;sys_created_on&gt;2024-11-25 16:56:51&lt;/sys_created_on&gt;&lt;sys_id&gt;cc68119683465a1000d5ccc0deaad3c3&lt;/sys_id&gt;&lt;sys_mod_count&gt;4&lt;/sys_mod_count&gt;&lt;sys_name&gt;GetBaseRecordTables&lt;/sys_name&gt;&lt;sys_package display_value="R-IDE WORK IN PROGRESS" source="x_snc_ide"&gt;b598b2161b2e2510cd6153d16b4bcb08&lt;/sys_package&gt;&lt;sys_policy&gt;read&lt;/sys_policy&gt;&lt;sys_scope display_value="R-IDE WORK IN PROGRESS"&gt;b598b2161b2e2510cd6153d16b4bcb08&lt;/sys_scope&gt;&lt;sys_update_name&gt;sys_script_include_cc68119683465a1000d5ccc0deaad3c3&lt;/sys_update_name&gt;&lt;sys_updated_by&gt;admin&lt;/sys_updated_by&gt;&lt;sys_updated_on&gt;2024-12-08 00:03:52&lt;/sys_updated_on&gt;&lt;/sys_script_include&gt;&lt;/record_update&gt;</payload>
        <payload_hash>1795912852</payload_hash>
        <record_name>GetBaseRecordTables</record_name>
        <reverted_from/>
        <source>bf883c7083d6965000d5ccc0deaad395</source>
        <source_table>sys_update_set</source_table>
        <state>previous</state>
        <sys_created_by>admin</sys_created_by>
        <sys_created_on>2024-12-08 00:03:53</sys_created_on>
        <sys_id>9c3dec96c3161e505a37f907050131ce</sys_id>
        <sys_mod_count>0</sys_mod_count>
        <sys_recorded_at>193a3946a660000001</sys_recorded_at>
        <sys_updated_by>admin</sys_updated_by>
        <sys_updated_on>2024-12-08 00:03:53</sys_updated_on>
        <type>Script Include</type>
        <update_guid>143dec962b161e50dc24613277b078ce</update_guid>
        <update_guid_history>143dec962b161e50dc24613277b078ce:1795912852,ccfa115a15465a10daef48258e2ae1d7:-1183302547,d0e89d96c1465a101afe744b6adbc2f1:-2051867133,b2d89d967c465a102cfd563a583e1251:-567902202,0c68119625465a105d98835e3d33cfc6:809211891</update_guid_history>
    </sys_update_version>
    <sys_metadata_delete action="INSERT_OR_UPDATE">
        <sys_audit_delete/>
        <sys_class_name>sys_metadata_delete</sys_class_name>
        <sys_created_by>admin</sys_created_by>
        <sys_created_on>2024-12-08 17:27:15</sys_created_on>
        <sys_db_object display_value="" name="sys_script_include">sys_script_include</sys_db_object>
        <sys_id>a59226ec9cdd45be98c14d362aa1d4c1</sys_id>
        <sys_metadata>cc68119683465a1000d5ccc0deaad3c3</sys_metadata>
        <sys_mod_count>0</sys_mod_count>
        <sys_name>GetBaseRecordTables</sys_name>
        <sys_package display_value="R-IDE WORK IN PROGRESS" source="x_snc_ide">b598b2161b2e2510cd6153d16b4bcb08</sys_package>
        <sys_parent/>
        <sys_policy>read</sys_policy>
        <sys_scope display_value="R-IDE WORK IN PROGRESS">b598b2161b2e2510cd6153d16b4bcb08</sys_scope>
        <sys_scope_delete display_value="">2a091410ba074d5883e73b1420808590</sys_scope_delete>
        <sys_update_name>sys_script_include_cc68119683465a1000d5ccc0deaad3c3</sys_update_name>
        <sys_update_version display_value="sys_script_include_cc68119683465a1000d5ccc0deaad3c3">9c3dec96c3161e505a37f907050131ce</sys_update_version>
        <sys_updated_by>admin</sys_updated_by>
        <sys_updated_on>2024-12-08 17:27:15</sys_updated_on>
    </sys_metadata_delete>
</record_update>
